sdl_example_package/__init__.py
sdl_example_package/arithmetic.py
sdl_example_package/gdf_analysis.py
sdl_example_package/messaging.py
sdl_example_package/utilities/__init__.py
sdl_example_package/utilities/data_handling.py
sdl_example_package/utilities/number_handling.py
sdl_example_package-0.0.2.dist-info/LICENSE
sdl_example_package-0.0.2.dist-info/METADATA
sdl_example_package-0.0.2.dist-info/WHEEL
sdl_example_package-0.0.2.dist-info/top_level.txt
sdl_example_package-0.0.2.dist-info/RECORD
