Metadata-Version: 2.1
Name: sdl-example-package
Version: 0.0.2
Summary: An example package for use with Umiverse
Author-email: Sam Wolk <szvsw@mit.edu>
License: MIT License
Project-URL: Documentation, https://ubem.io
Project-URL: Repository, https://github.com/szvsw/sdl-package-demo
Classifier: Development Status :: 4 - Beta
Classifier: Intended Audience :: Science/Research
Classifier: License :: OSI Approved :: MIT License
Classifier: Programming Language :: Python :: 3.7
Classifier: Programming Language :: Python :: 3.8
Classifier: Programming Language :: Python :: 3.9
Requires-Python: >=3.7
License-File: LICENSE
Requires-Dist: geopandas
Requires-Dist: pandas
